Metadata-Version: 2.1
Name: easysockets
Version: 1.0.0
Summary: A Python module that allows you to create and use simple sockets.
Home-page: https://github.com/Matthias1590/EasySockets
Author: Matthias Wijnsma
Author-email: matthiasx95@gmail.com
License: MIT
Platform: UNKNOWN
Requires-Python: >=3.6
